simpletree3/__init__.py
simpletree3/algorithms.py
simpletree3/nodes.py
simpletree3-1.1.0.dist-info/LICENSE
simpletree3-1.1.0.dist-info/METADATA
simpletree3-1.1.0.dist-info/WHEEL
simpletree3-1.1.0.dist-info/top_level.txt
simpletree3-1.1.0.dist-info/RECORD
