Metadata-Version: 2.1
Name: simpletree3
Version: 1.1.0
Summary: A simple tree structure and associated search/iteration tools for python 3.4+. If found, uses cython for compilation.
Author: arcombe012
License:                                  Apache License
Project-URL: source, https://github.com/arcombe012/simpletree3.git
Keywords: tree,tree structure,python3 tree class
Classifier: Programming Language :: Python
Classifier: Programming Language :: Python :: 3 :: Only
Classifier: Operating System :: OS Independent
Classifier: Development Status :: 4 - Beta
Classifier: Intended Audience :: Developers
Classifier: License :: OSI Approved :: Apache Software License
Classifier: Topic :: Software Development :: Libraries
Classifier: Topic :: Software Development :: Libraries :: Python Modules
Requires-Python: >=3.4
License-File: LICENSE
